pushpin/__init__.py
pushpin/__main__.py
pushpin/commands.py
pushpin/pushpin.sh.py
pushpin-0.5.0.dist-info/entry_points.txt
pushpin-0.5.0.dist-info/LICENSE
pushpin-0.5.0.dist-info/WHEEL
pushpin-0.5.0.dist-info/METADATA
pushpin-0.5.0.dist-info/RECORD
