Metadata-Version: 2.1
Name: pushpin
Version: 0.5.0
Summary: Git hooks for python 📌
Home-page: https://github.com/nyanye/pushpin
License: MIT
Author: Jung Daun
Author-email: iam@nyanye.com
Requires-Python: >=3.7.2
Classifier: License :: OSI Approved :: MIT License
Classifier: Programming Language :: Python :: 3
Classifier: Programming Language :: Python :: 3.10
Classifier: Programming Language :: Python :: 3.8
Classifier: Programming Language :: Python :: 3.9
Project-URL: Repository, https://github.com/nyanye/pushpin
